{
  "project_info": {
    "project_number": "797337219685",
    "firebase_url": "https://researcher-app-79f5c.firebaseio.com",
    "project_id": "researcher-app-79f5c",
    "storage_bucket": "researcher-app-79f5c.appspot.com"
  },
  "client": [
    {
      "client_info": {
        "mobilesdk_app_id": "1:797337219685:android:f19c0b4fcd4caa5f9b4c8c",
        "android_client_info": {
          "package_name": "com.jeryldev.authentication_app"
        }
      },
      "oauth_client": [
        {
          "client_id": "797337219685-pm70d5pkg1b5mnnn73431pbgq6imd283.apps.googleusercontent.com",
          "client_type": 1,
          "android_info": {
            "package_name": "com.jeryldev.authentication_app",
            "certificate_hash": "6acb97334238450168c0be6679b68ea909fc045d"
          }
        },
        {
          "client_id": "797337219685-dig00dfp9fmmha3lref03le9u4gmhca2.apps.googleusercontent.com",
          "client_type": 3
        }
      ],
      "api_key": [
        {
          "current_key": "AIzaSyCWX8zhe_3A7aCjmwrEt_3QURbgOCsFnSY"
        }
      ],
      "services": {
        "appinvite_service": {
          "other_platform_oauth_client": [
            {
              "client_id": "797337219685-dig00dfp9fmmha3lref03le9u4gmhca2.apps.googleusercontent.com",
              "client_type": 3
            }
          ]
        }
      }
    }
  ],
  "configuration_version": "1"
}